chemical_safety/__init__.py
chemical_safety/chemical/2024_09_24_convertjsontoSQL.py
chemical_safety/chemical/__init__.py
chemical_safety/chemical/chemical.py
chemical_safety/chemical/molecule.py
chemical_safety/chemical/periodictable.py
chemical_safety/chemical/sigfig.py
chemical_safety/chemical/units.py
chemical_safety/chemical/lists/EPA_D_List.csv
chemical_safety/chemical/lists/EPA_P_List.csv
chemical_safety/chemical/lists/EPA_U_List.csv
chemical_safety/chemical/lists/IARC_classification.csv
chemical_safety/chemical/lists/NTP_anticipated_carcinogens.csv
chemical_safety/chemical/lists/NTP_known_carcinogens.csv
chemical_safety/chemical/lists/OSHA_carcinogens.csv
chemical_safety/chemical/lists/UMN_peroxide_formers.csv
chemical_safety/chemical/lists/convert_UMN_peroxide_list.py
chemical_safety/chemical/lists/convert_p_statements.py
chemical_safety/chemical/lists/p_statements.csv
chemical_safety/chemical/lists/process_EPA_lists.py
chemical_safety/chemical/lists/process_lists.py
chemical_safety/chemical/pictograms/Acute Toxic.svg
chemical_safety/chemical/pictograms/Acute_Toxic.svg
chemical_safety/chemical/pictograms/Compressed Gas.svg
chemical_safety/chemical/pictograms/Compressed_Gas.svg
chemical_safety/chemical/pictograms/Corrosive.svg
chemical_safety/chemical/pictograms/Environmental Hazard.svg
chemical_safety/chemical/pictograms/Environmental_Hazard.svg
chemical_safety/chemical/pictograms/Explosive.svg
chemical_safety/chemical/pictograms/Flammable.svg
chemical_safety/chemical/pictograms/Health Hazard.svg
chemical_safety/chemical/pictograms/Health_Hazard.svg
chemical_safety/chemical/pictograms/Irritant.svg
chemical_safety/chemical/pictograms/Oxidizing.svg
chemical_safety/chemical/tables/elements.csv
chemical_safety/dashboard/__init__.py
chemical_safety/dashboard/app.py
chemical_safety/dashboard/config.json
chemical_safety/dashboard/static/courses/CHEM1115/16 The Use of Melting Points in the Identification of Organic Compounds.txt
chemical_safety-1.1.1.dist-info/LICENSE
chemical_safety-1.1.1.dist-info/METADATA
chemical_safety-1.1.1.dist-info/WHEEL
chemical_safety-1.1.1.dist-info/entry_points.txt
chemical_safety-1.1.1.dist-info/top_level.txt
chemical_safety-1.1.1.dist-info/RECORD
