Metadata-Version: 2.1
Name: chemical-safety
Version: 1.1.1
Summary: A package for retreiving chemical safety information
Home-page: https://github.com/dpagonis/chemical_safety
Author: Demetrios Pagonis
Author-email: demetriospagonis@weber.edu
License-File: LICENSE
Requires-Dist: pandas
Requires-Dist: numpy
Requires-Dist: jinja2
Requires-Dist: requests
Requires-Dist: Levenshtein
Requires-Dist: natsort
Requires-Dist: flask
Requires-Dist: scipy
Requires-Dist: rdkit
Requires-Dist: reportlab
